gpswe
